{"Table": [{"rowcount": 4}], "Table1": [{"rownum": 1, "storeName": "湛江城市广场", "addressDetail": "人民大道南路42号城市广场首层", "pro": "24小时,Wi-Fi,点唱机,店内参观,礼品卡,生日餐会", "provinceName": "广东省", "cityName": "湛江市"}, {"rownum": 2, "storeName": "康顺", "addressDetail": "椹川大道北376号,湛江赤坎嘉信茂广场01层05/06室", "pro": "24小时,Wi-Fi,店内参观,礼品卡,生日餐会", "provinceName": "广东省", "cityName": "湛江市"}, {"rownum": 3, "storeName": "湛江万达", "addressDetail": "经济技术开发区海滨大道中128号", "pro": "Wi-Fi,店内参观,生日餐会", "provinceName": "广东省", "cityName": "湛江市"}, {"rownum": 4, "storeName": "湛江西站二", "addressDetail": "湛江西高铁站二层", "pro": "精选店", "provinceName": "广东省", "cityName": "湛江市"}]}